<annotation><folder /><filename>Grau_lang5_v2.jpg</filename><source><database>Unknown</database><annotation>Unknown</annotation><image>Unknown</image></source><size><width>373.0167510482529</width><height>252.73695449464904</height><depth /></size><segmented>0</segmented><object><name>Grau_lang</name><truncated>0</truncated><occluded>0</occluded><difficult>0</difficult><bndbox><xmin>76.55465512475172</xmin><ymin>140.27101552739114</ymin><xmax>449.5714061730046</xmax><ymax>393.0079700220402</ymax></bndbox><attributes><attribute><name>rotation</name><value>0.0</value></attribute></attributes></object></annotation>