<annotation><folder /><filename>Kappe7_v11.jpg</filename><source><database>Unknown</database><annotation>Unknown</annotation><image>Unknown</image></source><size><width>117.22530355159591</width><height>128.17090205199972</height><depth /></size><segmented>0</segmented><object><name>Kappe</name><truncated>0</truncated><occluded>0</occluded><difficult>0</difficult><bndbox><xmin>210.9443733863501</xmin><ymin>187.42320567840048</ymin><xmax>328.169676937946</xmax><ymax>315.5941077304002</ymax></bndbox><attributes><attribute><name>rotation</name><value>0.0</value></attribute></attributes></object></annotation>