<annotation><folder /><filename>Kappe4_v8.jpg</filename><source><database>Unknown</database><annotation>Unknown</annotation><image>Unknown</image></source><size><width>47.723746376595756</width><height>83.14870025504604</height><depth /></size><segmented>0</segmented><object><name>Kappe</name><truncated>0</truncated><occluded>0</occluded><difficult>0</difficult><bndbox><xmin>214.60121303244804</xmin><ymin>263.6411332500355</ymin><xmax>262.3249594090438</xmax><ymax>346.78983350508156</ymax></bndbox><attributes><attribute><name>rotation</name><value>0.0</value></attribute></attributes></object></annotation>