<annotation><folder /><filename>Rad22_v14.jpg</filename><source><database>Unknown</database><annotation>Unknown</annotation><image>Unknown</image></source><size><width>126.64696235010464</width><height>416.0916204140803</height><depth /></size><segmented>0</segmented><object><name>Rad</name><truncated>0</truncated><occluded>0</occluded><difficult>0</difficult><bndbox><xmin>158.49657752508162</xmin><ymin>0.0</ymin><xmax>285.14353987518626</xmax><ymax>416.0916204140803</ymax></bndbox><attributes><attribute><name>rotation</name><value>0.0</value></attribute></attributes></object></annotation>